{
  "generatedAt": "2026-07-04T03:55:43.503Z",
  "celebrities": [
    {
      "id": 287,
      "name": "Brad Pitt",
      "popularity": 10.7,
      "isAlive": true,
      "birthYear": 1963,
      "deathDate": null,
      "deathAge": null,
      "profilePath": "/m09Y1YfPPeNYYUSHnnVqahkrC1o.jpg",
      "knownFor": [
        "Inglourious Basterds",
        "World War Z",
        "Fight Club"
      ]
    },
    {
      "id": 1907997,
      "name": "Min Do-yoon",
      "popularity": 25.9,
      "isAlive": true,
      "birthYear": 1983,
      "deathDate": null,
      "deathAge": null,
      "profilePath": "/bHHn3krbHyxQIWb4JbHkPlV6Uu1.jpg",
      "knownFor": [
        "24 Year Old Yoon Yul's Sexy Breasts",
        "Beauty Salon: Special Service 3",
        "Beauty Salon: Special Service 4"
      ]
    },
    {
      "id": 1562430,
      "name": "Hannah Cheramy",
      "popularity": 18,
      "isAlive": true,
      "birthYear": 2003,
      "deathDate": null,
      "deathAge": null,
      "profilePath": "/bVNJpvLKWwzxvLPFFmhsoMsR5qu.jpg",
      "knownFor": [
        "FROM",
        "Colossal",
        "The Hollow Child"
      ]
    },
    {
      "id": 588,
      "name": "M. Emmet Walsh",
      "popularity": 38.1,
      "isAlive": false,
      "birthYear": 1935,
      "deathDate": "2024-03-19",
      "deathAge": 88,
      "profilePath": "/fVWvBxvwyk4aTA9vKZOV9qHRNNk.jpg",
      "knownFor": [
        "Blade Runner",
        "Knives Out",
        "Wild Wild West"
      ]
    },
    {
      "id": 742,
      "name": "Michael Byrne",
      "popularity": 11.9,
      "isAlive": false,
      "birthYear": 1943,
      "deathDate": "2026-06-20",
      "deathAge": 82,
      "profilePath": "/cWUhkJPdyPFbWAskmTuzgEXYR8X.jpg",
      "knownFor": [
        "Indiana Jones and the Last Crusade",
        "Braveheart",
        "Harry Potter and the Deathly Hallows: Part 1"
      ]
    }
  ]
}